LICENSE
MANIFEST.in
README.md
pyproject.toml
requirements-build.txt
setup.py
./csrc/binding.cpp
./csrc/fused_shared_experts_kernel.cu
./csrc/moe_align_kernel.cu
chitu/__init__.py
chitu/__main__.py
chitu/async_response.py
chitu/attn_backend.py
chitu/backend.py
chitu/cache_manager.py
chitu/chitu_main.py
chitu/cuda_graph.py
chitu/device_list.py
chitu/device_type.py
chitu/executor.py
chitu/fused_moe.py
chitu/global_vars.py
chitu/muxi_utils.py
chitu/ops.py
chitu/scheduler.py
chitu/serve.py
chitu/static_tensor.py
chitu/task.py
chitu/tensor_parallel.py
chitu/tokenizer.py
chitu/triton_decode_attention.py
chitu/triton_kernels.py
chitu/utils.py
chitu.egg-info/PKG-INFO
chitu.egg-info/SOURCES.txt
chitu.egg-info/dependency_links.txt
chitu.egg-info/requires.txt
chitu.egg-info/top_level.txt
chitu/awq/__init__.py
chitu/awq/auto_clip.py
chitu/awq/auto_scale.py
chitu/awq/qmodule.py
chitu/config/serve_config.yaml
chitu/config/serve_config_awq.yaml
chitu/config/serve_config_gptq.yaml
chitu/config/serve_config_llmint8.yaml
chitu/config/serve_config_simple_w8a8.yaml
chitu/config/serve_config_simple_w8a8_muxi.yaml
chitu/config/serve_config_w8a16.yaml
chitu/config/models/DeepSeek-R1-Distill-Qwen-14B.yaml
chitu/config/models/DeepSeek-R1-bf16.yaml
chitu/config/models/DeepSeek-R1.yaml
chitu/config/models/Meta-Llama-3-8B-Instruct-original.yaml
chitu/config/models/Mixtral-8x7B-Instruct-v0.1.yaml
chitu/config/models/QwQ-32B.yaml
chitu/config/models/Qwen2-72B-Instruct.yaml
chitu/config/models/Qwen2-7B-Instruct.yaml
chitu/config/models/glm-4-9b-chat.yaml
chitu/models/__init__.py
chitu/models/model.py
chitu/models/model_deepseek_v3.py
chitu/models/model_hf_llama.py
chitu/models/model_hf_mixtral.py
chitu/models/model_llama.py
chitu/quantize/__init__.py
chitu/quantize/muxi_w8a8.py
chitu/quantize/quantizer.py
chitu/quantize/w8a16.py
chitu/quantize/w8a8.py
csrc/binding.cpp
csrc/common.h
csrc/fused_shared_experts_kernel.cu
csrc/moe_align_kernel.cu
csrc/moe_kernel.h
docs/CONTRIBUTING.md
docs/Development.md
docs/WeChatGroup.png
docs/assets/wechat-assistant.png
docs/en/FAQ.md
docs/zh/FAQ.md
docs/zh/README_zh.md
test/test_eval.py
