Metadata-Version: 2.4
Name: chitu
Version: 0.1.2
Summary: A high-performance inference framework for large language models, focusing on efficiency, flexibility, and availability.
Project-URL: Homepage, https://github.com/thu-pacman/chitu
Project-URL: Issues, https://github.com/thu-pacman/chitu/issues
Classifier: Programming Language :: Python :: 3
Requires-Python: >=3.8
License-File: LICENSE
Requires-Dist: setuptools
Requires-Dist: wheel
Requires-Dist: cmake
Requires-Dist: ninja
Requires-Dist: protobuf
Requires-Dist: sentencepiece
Requires-Dist: cython
Requires-Dist: packaging
Requires-Dist: accelerate
Requires-Dist: transformers
Requires-Dist: fire
Requires-Dist: tiktoken>=0.7.0
Requires-Dist: blobfile
Requires-Dist: faker
Requires-Dist: hydra-core
Requires-Dist: fastapi
Requires-Dist: uvicorn
Requires-Dist: tqdm
Requires-Dist: bitsandbytes
Requires-Dist: einops
Requires-Dist: flashinfer-python
Dynamic: license-file
